pylord/__init__.py
pylord/app.py
pylord/asgi.py
pylord/asgi_response.py
pylord/middleware.py
pylord/orm.py
pylord/response.py
pylord-0.3.0.dist-info/METADATA
pylord-0.3.0.dist-info/WHEEL
pylord-0.3.0.dist-info/top_level.txt
pylord-0.3.0.dist-info/RECORD
