Metadata-Version: 2.1
Name: pylord
Version: 0.3.0
Summary: Python web framework building for APIs
Home-page: https://github.com/ravshanovdev/Sauron
Author: Kamoliddin Ravshanov
Author-email: kravshanov97@gmail.com
License: MIT
Classifier: License :: OSI Approved :: MIT License
Classifier: Programming Language :: Python
Classifier: Programming Language :: Python :: 3
Classifier: Programming Language :: Python :: 3.6
Classifier: Programming Language :: Python :: Implementation :: CPython
Classifier: Programming Language :: Python :: Implementation :: PyPy
Requires-Python: >=3.9.0
Requires-Dist: Jinja2==3.1.4
Requires-Dist: parse==1.20.2
Requires-Dist: WebOb==1.8.9
Requires-Dist: whitenoise==6.8.2
Requires-Dist: requests==2.32.3
Requires-Dist: requests-wsgi-adapter==0.4.1
Requires-Dist: starlette==0.48.0
